Workbook

Sheet Custos por app
A1: Tudo o que vamos gastar, por aplicativo/serviço
A2: Valores de referência (out/2026). Azul = valor que você pode editar. "Quando" diz se é preciso já, no lançamento ou só depois.
A4: Aplicativo / serviço | B4: Para que serve | C4: Quando | D4: Cobrança | E4: Valor (US$) | F4: Valor (R$) | G4: Custo mensal (R$) | H4: Agora (teste) R$/mês | I4: Obrigatório? | J4: Observação
A5: Render (servidor do site e do app) | B5: Deixa o site e o app no ar | C5: Lançamento | D5: Mensal | E5: 7 | F5: =E5*Premissas!$B$4 -> 38.5 | G5: =F5 -> 38.5 | H5: 0 | I5: Sim | J5: Grátis hoje, mas "dorme" e demora ~1 min para abrir. Plano Starter antes de divulgar.
A6: Neon (banco de dados) | B6: Guarda empresas, avaliações, agendamentos | C6: Crescimento | D6: Mensal | E6: 19 | F6: =E6*Premissas!$B$4 -> 104.5 | G6: =F6 -> 104.5 | H6: 0 | I6: Sim | J6: Plano grátis aguenta o começo. Estimativa US$ 19–30 quando crescer; confira o preço no site da Neon.
A7: Anthropic / Claude (IA) | B7: Assistente de IA das empresas | C7: Agora | D7: Por uso | F7: ver Resumo | G7: 0 | H7: 0 | I7: Não | J7: Calculado na aba Resumo mensal (custo por uso × usos). Sem chave, o assistente fica desligado.
A8: Asaas (pagamentos) | B8: Recebe Pix e cartão das empresas | C8: Lançamento | D8: Por cobrança | F8: ver Resumo | G8: 0 | H8: 0 | I8: Sim | J8: Sem mensalidade: cobra uma taxa por pagamento recebido (aba Resumo mensal).
A9: Google Play Console | B9: Publicar o app Android | C9: Agora | D9: Única vez | E9: 25 | F9: =E9*Premissas!$B$4 -> 137.5 | G9: 0 | H9: 0 | I9: Sim | J9: Pagamento único (US$ 25). Se já pagou, coloque 0 no valor.
A10: Apple Developer Program | B10: Publicar o app no iPhone | C10: Depois | D10: Anual | E10: 99 | F10: =E10*Premissas!$B$4 -> 544.5 | G10: =F10/12 -> 45.375 | H10: 0 | I10: Para iPhone | J10: US$ 99 por ano. Só quando for lançar na App Store.
A11: Build do iPhone na nuvem (ex.: Codemagic) | B11: Gerar o app iOS sem ter Mac | C11: Depois | D11: Mensal | E11: 0 | F11: =E11*Premissas!$B$4 -> 0 | G11: =F11 -> 0 | H11: 0 | I11: Para iPhone | J11: Plano grátis costuma bastar para poucos builds por mês.
A12: Domínio .com.br (Registro.br) | B12: Endereço próprio (ex.: conectalocal.com.br) | C12: Lançamento | D12: Anual | F12: 40 | G12: =F12/12 -> 3.3333333 | H12: 0 | I12: Recomendado | J12: R$ 40 por ano. Passa mais confiança que o endereço onrender.com.
A13: Contador | B13: Abrir e manter o CNPJ, impostos | C13: Lançamento | D13: Mensal | F13: 250 | G13: =F13 -> 250 | H13: 0 | I13: Sim (com CNPJ) | J13: Estimativa R$ 150–400/mês; contabilidade on-line costuma ser mais barata.
A14: GitHub | B14: Guarda o código do app | C14: Agora | D14: Grátis | E14: 0 | F14: =E14*Premissas!$B$4 -> 0 | G14: 0 | H14: 0 | I14: Sim | J14: Plano grátis é suficiente.
A15: PWABuilder | B15: Gera o pacote do app para a Play Store | C15: Agora | D15: Grátis | E15: 0 | F15: =E15*Premissas!$B$4 -> 0 | G15: 0 | H15: 0 | I15: Sim | J15: Gratuito.
A16: cron-job.org | B16: Evita o servidor grátis "dormir" (só fase de teste) | C16: Agora | D16: Grátis | E16: 0 | F16: =E16*Premissas!$B$4 -> 0 | G16: 0 | H16: 0 | I16: Não | J16: Dispensável depois de mudar para o Render Starter.
A17: Total de custos fixos | G17: =SUM(G5:G16) -> 441.70833 | H17: =SUM(H5:H16) -> 0
A18: Gastos de uma vez só (Play Console) | F18: =SUMIFS(F5:F16,D5:D16,"Única vez") -> 137.5
A19: Gastos anuais (Apple + domínio) | F19: =SUMIFS(F5:F16,D5:D16,"Anual") -> 584.5
A21: Fase de teste (coluna H): tudo no plano grátis. Mude o valor se começar a pagar algo antes do lançamento.

Sheet Premissas
A1: Premissas (edite só as células em azul com fundo amarelo)
A3: Premissa | B3: Valor | C3: Observação
A4: Cotação do dólar (R$) | B4: 5.5 | C4: Ajuste para a cotação do dia.
A5: Preço plano Profissional (R$/mês) | B5: 49.9 | C5: Definido no app (packages/shared/src/panel.ts).
A6: Preço plano Equipe (R$/mês) | B6: 99.9 | C6: Definido no app.
A7: Custo da IA por uso (R$) | B7: 0.14 | C7: Modelo padrão (Opus): ~1.500 tokens entrada + 1.000 saída ≈ US$ 0,026. Com Haiku cai para ~R$ 0,004.
A8: Usos de IA por empresa grátis (mês) | B8: 5 | C8: Limite do plano é 10; estimativa de uso médio.
A9: Usos de IA por empresa Profissional (mês) | B9: 40 | C9: Limite 80; estimativa de uso médio.
A10: Usos de IA por empresa Equipe (mês) | B10: 120 | C10: Limite 250; estimativa de uso médio.
A11: Taxa média do meio de pagamento (Asaas) | B11: 0.04 | C11: Estimativa média entre Pix e cartão. Confira as taxas da sua conta Asaas.
A12: Imposto (Simples Nacional) | B12: 0.06 | C12: Estimativa 6%–8% (Anexo III). Confirme com um contador.

Sheet Resumo mensal
A1: Quanto gastamos e quanto sobra por mês (3 cenários)
A2: Edite o número de empresas (azul). Tudo o mais é calculado.
A4: Item | B4: Começo | C4: 100 empresas | D4: 500 empresas
A5: Empresas no plano Grátis | B5: 40 | C5: 70 | D5: 340
A6: Empresas no plano Profissional | B6: 8 | C6: 24 | D6: 125
A7: Empresas no plano Equipe | B7: 2 | C7: 6 | D7: 35
A8: RECEITA
A9: Receita Profissional | B9: =B6*Premissas!$B$5 -> 399.2 | C9: =C6*Premissas!$B$5 -> 1197.6 | D9: =D6*Premissas!$B$5 -> 6237.5
A10: Receita Equipe | B10: =B7*Premissas!$B$6 -> 199.8 | C10: =C7*Premissas!$B$6 -> 599.4 | D10: =D7*Premissas!$B$6 -> 3496.5
A11: Receita total | B11: =B9+B10 -> 599 | C11: =C9+C10 -> 1797 | D11: =D9+D10 -> 9734
A12: GASTOS
A13: Custos fixos (Render, Neon, contador, domínio, Apple) | B13: ='Custos por app'!$G$17 -> 441.70833 | C13: ='Custos por app'!$G$17 -> 441.70833 | D13: ='Custos por app'!$G$17 -> 441.70833
A14: IA (Claude) | B14: =(B5*Premissas!$B$8+B6*Premissas!$B$9+B7*Premissas!$B$10)*Premissas!$B$7 -> 106.4 | C14: =(C5*Premissas!$B$8+C6*Premissas!$B$9+C7*Premissas!$B$10)*Premissas!$B$7 -> 284.2 | D14: =(D5*Premissas!$B$8+D6*Premissas!$B$9+D7*Premissas!$B$10)*Premissas!$B$7 -> 1526
A15: Taxas do Asaas | B15: =B11*Premissas!$B$11 -> 23.96 | C15: =C11*Premissas!$B$11 -> 71.88 | D15: =D11*Premissas!$B$11 -> 389.36
A16: Impostos | B16: =B11*Premissas!$B$12 -> 35.94 | C16: =C11*Premissas!$B$12 -> 107.82 | D16: =D11*Premissas!$B$12 -> 584.04
A17: Gasto total | B17: =SUM(B13:B16) -> 608.00833 | C17: =SUM(C13:C16) -> 905.60833 | D17: =SUM(D13:D16) -> 2941.1083
A18: RESULTADO
A19: Lucro por mês | B19: =B11-B17 -> -9.0083333 | C19: =C11-C17 -> 891.39167 | D19: =D11-D17 -> 6792.8917
A20: Margem | B20: =IF(B11=0,0,B19/B11) -> -0.015038954 | C20: =IF(C11=0,0,C19/C11) -> 0.49604433 | D20: =IF(D11=0,0,D19/D11) -> 0.69785203
A21: Lucro por ano | B21: =B19*12 -> -108.1 | C21: =C19*12 -> 10696.7 | D21: =D19*12 -> 81514.7
A23: Observações
A24: • Custos fixos vêm da aba "Custos por app" (já com Render Starter, Neon pago, contador, domínio e Apple divididos por mês).
A25: • No começo, Neon e contador podem ficar no plano grátis / sem CNPJ: o gasto real será menor que o mostrado.
A26: • Taxas e impostos são estimativas: confirme com o Asaas e com um contador.
A27: • A Google Play (US$ 25) é paga uma vez só e não entra no mês.
